LICENSE
MANIFEST.in
README.md
package.json
setup.py
head_model/HeadModel.py
head_model/__init__.py
head_model/_imports_.py
head_model/async-HeadModel.js
head_model/async-HeadModel.js.map
head_model/head_model.min.js
head_model/head_model.min.js.map
head_model/metadata.json
head_model/package-info.json
head_model.egg-info/PKG-INFO
head_model.egg-info/SOURCES.txt
head_model.egg-info/dependency_links.txt
head_model.egg-info/top_level.txt
tests/test_usage.py