Metadata-Version: 2.1
Name: head_model
Version: 0.0.1
Summary: Test Component for integration of three.js rendering tool with dash components for head model rendering
Author: Bryan Jiang <bryanbj@umich.edu>
License: MIT
Classifier: Framework :: Dash
License-File: LICENSE
